mihto/__init__.py
mihto/mihto.py
mihto/evaluator/__init__.py
mihto/evaluator/evaluator.py
mihto/evaluator/exceptions.py
mihto/lexer/__init__.py
mihto/lexer/exceptions.py
mihto/lexer/lexer.py
mihto/lexer/token_types.py
mihto/parser/__init__.py
mihto/parser/exceptions.py
mihto/parser/nodes.py
mihto/parser/parser.py
mihto-0.0.5.dist-info/METADATA
mihto-0.0.5.dist-info/RECORD
mihto-0.0.5.dist-info/WHEEL
mihto-0.0.5.dist-info/top_level.txt
