Metadata-Version: 2.1
Name: mihto
Version: 0.0.5
Summary: Easy and simple evaluation language
Home-page: https://github.com/OrbitalAds/Mihto
Author: OrbitalAds
Author-email: dev@orbitalads.io
License: UNKNOWN
Keywords: evaluation evaluate language
Platform: UNKNOWN
Classifier: Development Status :: 3 - Alpha
Classifier: Intended Audience :: Developers
Classifier: Topic :: Software Development :: Build Tools
Classifier: License :: OSI Approved :: MIT License
Classifier: Natural Language :: Spanish
Classifier: Programming Language :: Python :: 3
Classifier: Programming Language :: Python :: 3.4
Classifier: Programming Language :: Python :: 3.5
Classifier: Programming Language :: Python :: 3.6
